gdpc/__init__.py
gdpc/block.py
gdpc/block_state_tools.py
gdpc/editor.py
gdpc/editor_tools.py
gdpc/exceptions.py
gdpc/geometry.py
gdpc/interface.py
gdpc/lookup.py
gdpc/minecraft_tools.py
gdpc/model.py
gdpc/nbt_tools.py
gdpc/py.typed
gdpc/transform.py
gdpc/utils.py
gdpc/vector_tools.py
gdpc/world_slice.py
gdpc-8.1.0.dist-info/LICENSE
gdpc-8.1.0.dist-info/METADATA
gdpc-8.1.0.dist-info/WHEEL
gdpc-8.1.0.dist-info/top_level.txt
gdpc-8.1.0.dist-info/RECORD
