Metadata-Version: 2.1
Name: gdpc
Version: 8.1.0
Summary: A python framework for procedural generation in Minecraft with the GDMC HTTP Interface mod.
Home-page: https://github.com/avdstaaij/gdpc
Author: Arthur van der Staaij, Blinkenlights, Nils Gawlik
Author-email: arthurvanderstaaij@gmail.com, blinkenlights@pm.me, nilsgawlik@gmx.de
Maintainer: Arthur van der Staaij
Maintainer-email: arthurvanderstaaij@gmail.com
License: MIT
Project-URL: Documentation, https://gdpc.readthedocs.io
Project-URL: Bug Reports, https://github.com/avdstaaij/gdpc/issues
Project-URL: Changelog, https://github.com/avdstaaij/gdpc/blob/master/CHANGELOG.md
Project-URL: Official Competition wiki, https://gendesignmc.wikidot.com/start
Project-URL: Chat about it on Discord, https://discord.gg/YwpPCRQWND
Project-URL: Source, https://github.com/avdstaaij/gdpc
Keywords: GDMC,generative design,Minecraft,HTTP,development
Classifier: Development Status :: 5 - Production/Stable
Classifier: Intended Audience :: Developers
Classifier: License :: OSI Approved :: MIT License
Classifier: Natural Language :: English
Classifier: Programming Language :: Python :: 3
Classifier: Topic :: Games/Entertainment :: Simulation
Classifier: Topic :: Software Development :: Libraries :: Application Frameworks
Classifier: Topic :: Software Development :: Version Control :: Git
Classifier: Typing :: Typed
Requires-Python: >=3.8, <4
License-File: LICENSE
Requires-Dist: Deprecated
Requires-Dist: matplotlib
Requires-Dist: more-itertools
Requires-Dist: NBT
Requires-Dist: numpy
Requires-Dist: opencv-python
Requires-Dist: PyGLM>=2.8.0
Requires-Dist: requests
Requires-Dist: scikit-image>=0.19.0
Requires-Dist: scipy
Requires-Dist: types-requests
Requires-Dist: typing-extensions
